nlplot/__init__.py
nlplot/nlplot.py
nlplot/data/mplus-1c-regular.ttf
nlplot-1.6.0.dist-info/LICENSE
nlplot-1.6.0.dist-info/METADATA
nlplot-1.6.0.dist-info/WHEEL
nlplot-1.6.0.dist-info/top_level.txt
nlplot-1.6.0.dist-info/RECORD
