Metadata-Version: 2.1
Name: nlplot
Version: 1.6.0
Summary: Visualization Module for Natural Language Processing
Home-page: https://github.com/takapy0210/nlplot
Author: Takanobu Nozawa
Author-email: takanobu.030210@gmail.com
License: MIT License
Requires-Python: >=3.6
License-File: LICENSE
Requires-Dist: pandas
Requires-Dist: numpy
Requires-Dist: tqdm
Requires-Dist: seaborn
Requires-Dist: plotly (>=4.12.0)
Requires-Dist: matplotlib
Requires-Dist: wordcloud
Requires-Dist: pillow
Requires-Dist: networkx
Requires-Dist: ipython
Requires-Dist: scikit-learn
